{"metadata":{"modules":{"imports":[],"exports":{"exported":[],"specifiers":[]}},"usedHelpers":[]},"ignored":false,"code":"/*!\r\n * Documenter 1.6\r\n * http://rxa.li/documenter\r\n *\r\n * Copyright 2011, Xaver Birsak\r\n * http://revaxarts.com\r\n *\r\n */\n//if Cufon replace headings\nif (typeof Cufon == 'function') Cufon.replace('h1, h2, h3, h4, h5, h6');\n\n$(document).ready(function () {\n\tvar timeout,\n\t    sections = new Array(),\n\t    sectionscount = 0,\n\t    win = $(window),\n\t    sidebar = $('#documenter_sidebar'),\n\t    nav = $('#documenter_nav'),\n\t    logo = $('#documenter_logo'),\n\t    navanchors = nav.find('a'),\n\t    timeoffset = 50,\n\t    hash = location.hash || null;\n\tiDeviceNotOS4 = navigator.userAgent.match(/iphone|ipod|ipad/i) && !navigator.userAgent.match(/OS 5/i) || false, badIE = $('html').prop('class').match(/ie(6|7|8)/) || false;\n\n\t//handle external links (new window)\n\t$('a[href^=http]').bind('click', function () {\n\t\twindow.open($(this).attr('href'));\n\t\treturn false;\n\t});\n\n\t//IE 8 and lower doesn't like the smooth pagescroll\n\tif (!badIE) {\n\t\twindow.scroll(0, 0);\n\n\t\t$('a[href^=#]').bind('click touchstart', function () {\n\t\t\thash = $(this).attr('href');\n\t\t\t$.scrollTo.window().queue([]).stop();\n\t\t\tgoTo(hash);\n\t\t\treturn false;\n\t\t});\n\n\t\t//if a hash is set => go to it\n\t\tif (hash) {\n\t\t\tsetTimeout(function () {\n\t\t\t\tgoTo(hash);\n\t\t\t}, 500);\n\t\t}\n\t}\n\n\t//We need the position of each section until the full page with all images is loaded\n\twin.bind('load', function () {\n\n\t\tvar sectionselector = 'section';\n\n\t\t//Documentation has subcategories\t\t\n\t\tif (nav.find('ol').length) {\n\t\t\tsectionselector = 'section, h4';\n\t\t}\n\t\t//saving some information\n\t\t$(sectionselector).each(function (i, e) {\n\t\t\tvar _this = $(this);\n\t\t\tvar p = {\n\t\t\t\tid: this.id,\n\t\t\t\tpos: _this.offset().top\n\t\t\t};\n\t\t\tsections.push(p);\n\t\t});\n\n\t\t//iPhone, iPod and iPad don't trigger the scroll event\n\t\tif (iDeviceNotOS4) {\n\t\t\tnav.find('a').bind('click', function () {\n\t\t\t\tsetTimeout(function () {\n\t\t\t\t\twin.trigger('scroll');\n\t\t\t\t}, duration);\n\t\t\t});\n\t\t\t//scroll to top\n\t\t\twindow.scroll(0, 0);\n\t\t}\n\n\t\t//how many sections\n\t\tsectionscount = sections.length;\n\n\t\t//bind the handler to the scroll event\n\t\twin.bind('scroll', function (event) {\n\t\t\tclearInterval(timeout);\n\t\t\t//should occur with a delay\n\t\t\ttimeout = setTimeout(function () {\n\t\t\t\t//get the position from the very top in all browsers\n\t\t\t\tpos = window.pageYOffset || document.documentElement.scrollTop || document.body.scrollTop;\n\n\t\t\t\t//iDeviceNotOS4s don't know the fixed property so we fake it\n\t\t\t\tif (iDeviceNotOS4) {\n\t\t\t\t\tsidebar.css({ height: document.height });\n\t\t\t\t\tlogo.css({ 'margin-top': pos });\n\t\t\t\t}\n\t\t\t\t//activate Nav element at the current position\n\t\t\t\tactivateNav(pos);\n\t\t\t}, timeoffset);\n\t\t}).trigger('scroll');\n\t});\n\n\t//the function is called when the hash changes\n\tfunction hashchange() {\n\t\tgoTo(location.hash, false);\n\t}\n\n\t//scroll to a section and set the hash\n\tfunction goTo(hash, changehash) {\n\t\twin.unbind('hashchange', hashchange);\n\t\thash = hash.replace(/!\\//, '');\n\t\twin.stop().scrollTo(hash, duration, {\n\t\t\teasing: easing,\n\t\t\taxis: 'y'\n\t\t});\n\t\tif (changehash !== false) {\n\t\t\tvar l = location;\n\t\t\tlocation.href = l.protocol + '//' + l.host + l.pathname + '#!/' + hash.substr(1);\n\t\t}\n\t\twin.bind('hashchange', hashchange);\n\t}\n\n\t//activate current nav element\n\tfunction activateNav(pos) {\n\t\tvar offset = 100,\n\t\t    current,\n\t\t    next,\n\t\t    parent,\n\t\t    isSub,\n\t\t    hasSub;\n\t\twin.unbind('hashchange', hashchange);\n\t\tfor (var i = sectionscount; i > 0; i--) {\n\t\t\tif (sections[i - 1].pos <= pos + offset) {\n\t\t\t\tnavanchors.removeClass('current');\n\t\t\t\tcurrent = navanchors.eq(i - 1);\n\t\t\t\tcurrent.addClass('current');\n\n\t\t\t\tparent = current.parent().parent();\n\t\t\t\tnext = current.next();\n\n\t\t\t\thasSub = next.is('ol');\n\t\t\t\tisSub = !parent.is('#documenter_nav');\n\n\t\t\t\tnav.find('ol:visible').not(parent).slideUp('fast');\n\t\t\t\tif (isSub) {\n\t\t\t\t\tparent.prev().addClass('current');\n\t\t\t\t\tparent.stop().slideDown('fast');\n\t\t\t\t} else if (hasSub) {\n\t\t\t\t\tnext.stop().slideDown('fast');\n\t\t\t\t}\n\t\t\t\twin.bind('hashchange', hashchange);\n\t\t\t\tbreak;\n\t\t\t};\n\t\t}\n\t}\n});","ast":null,"map":{"version":3,"sources":["/plugins/revolution-slider/documentation/js/script.js"],"names":[],"mappings":";;;;;;;;;AASA,IAAG,OAAO,KAAK,IAAI,UAAU,EAAE,KAAK,CAAC,OAAO,CAAC,wBAAwB,CAAC,CAAC;;AAEvE,CAAC,CAAC,QAAQ,CAAC,CAAC,KAAK,CAAC,YAAW;AAC5B,KAAI,OAAO;KACV,QAAQ,GAAG,IAAI,KAAK,EAAE;KACtB,aAAa,GAAG,CAAC;KACjB,GAAG,GAAG,CAAC,CAAC,MAAM,CAAC;KACf,OAAO,GAAG,CAAC,CAAC,qBAAqB,CAAC;KAClC,GAAG,GAAG,CAAC,CAAC,iBAAiB,CAAC;KAC1B,IAAI,GAAG,CAAC,CAAC,kBAAkB,CAAC;KAC5B,UAAU,GAAG,GAAG,CAAC,IAAI,CAAC,GAAG,CAAC;KAC1B,UAAU,GAAG,EAAE;KACf,IAAI,GAAG,QAAQ,CAAC,IAAI,IAAI,IAAI,CAAC;AAC7B,cAAa,GAAG,AAAC,SAAS,CAAC,SAAS,CAAC,KAAK,CAAC,mBAAmB,CAAC,IAAI,CAAC,SAAS,CAAC,SAAS,CAAC,KAAK,CAAC,OAAO,CAAC,IAAK,KAAK,EAChH,KAAK,GAAG,CAAC,CAAC,MAAM,CAAC,CAAC,IAAI,CAAC,OAAO,CAAC,CAAC,KAAK,CAAC,WAAW,CAAC,IAAG,KAAK,CAAC;;;AAG5D,EAAC,CAAC,eAAe,CAAC,CAAC,IAAI,CAAC,OAAO,EAAC,YAAU;AACzC,QAAM,CAAC,IAAI,CAAC,CAAC,CAAC,IAAI,CAAC,CAAC,IAAI,CAAC,MAAM,CAAC,CAAC,CAAC;AAClC,SAAO,KAAK,CAAC;EACb,CAAC,CAAC;;;AAGH,KAAG,CAAC,KAAK,EAAC;AACT,QAAM,CAAC,MAAM,CAAC,CAAC,EAAC,CAAC,CAAC,CAAC;;AAEnB,GAAC,CAAC,YAAY,CAAC,CAAC,IAAI,CAAC,kBAAkB,EAAC,YAAU;AACjD,OAAI,GAAG,CAAC,CAAC,IAAI,CAAC,CAAC,IAAI,CAAC,MAAM,CAAC,CAAC;AAC5B,IAAC,CAAC,QAAQ,CAAC,MAAM,EAAE,CAAC,KAAK,CAAC,EAAE,CAAC,CAAC,IAAI,EAAE,CAAC;AACrC,OAAI,CAAC,IAAI,CAAC,CAAC;AACX,UAAO,KAAK,CAAC;GACb,CAAC,CAAC;;;AAGH,MAAG,IAAI,EAAC;AACP,aAAU,CAAC,YAAU;AACpB,QAAI,CAAC,IAAI,CAAC,CAAC;IACX,EAAC,GAAG,CAAC,CAAC;GACP;EACD;;;AAID,IAAG,CAAC,IAAI,CAAC,MAAM,EAAC,YAAU;;AAEzB,MAAI,eAAe,GAAG,SAAS,CAAC;;;AAGhC,MAAG,GAAG,CAAC,IAAI,CAAC,IAAI,CAAC,CAAC,MAAM,EAAC;AACxB,kBAAe,GAAG,aAAa,CAAC;GAChC;;AAED,GAAC,CAAC,eAAe,CAAC,CAAC,IAAI,CAAC,UAAS,CAAC,EAAC,CAAC,EAAC;AACpC,OAAI,KAAK,GAAG,CAAC,CAAC,IAAI,CAAC,CAAC;AACpB,OAAI,CAAC,GAAG;AACP,MAAE,EAAE,IAAI,CAAC,EAAE;AACX,OAAG,EAAE,KAAK,CAAC,MAAM,EAAE,CAAC,GAAG;IACvB,CAAC;AACF,WAAQ,CAAC,IAAI,CAAC,CAAC,CAAC,CAAC;GACjB,CAAC,CAAC;;;AAIH,MAAG,aAAa,EAAC;AAChB,MAAG,CAAC,IAAI,CAAC,GAAG,CAAC,CAAC,IAAI,CAAC,OAAO,EAAC,YAAU;AACpC,cAAU,CAAC,YAAU;AACpB,QAAG,CAAC,OAAO,CAAC,QAAQ,CAAC,CAAC;KACtB,EAAC,QAAQ,CAAC,CAAC;IAEZ,CAAC,CAAC;;AAEH,SAAM,CAAC,MAAM,CAAC,CAAC,EAAC,CAAC,CAAC,CAAC;GACnB;;;AAGD,eAAa,GAAG,QAAQ,CAAC,MAAM,CAAC;;;AAGhC,KAAG,CAAC,IAAI,CAAC,QAAQ,EAAC,UAAS,KAAK,EAAC;AAChC,gBAAa,CAAC,OAAO,CAAC,CAAC;;AAEvB,UAAO,GAAG,UAAU,CAAC,YAAU;;AAE9B,OAAG,GAAG,MAAM,CAAC,WAAW,IAAI,QAAQ,CAAC,eAAe,CAAC,SAAS,IAAI,QAAQ,CAAC,IAAI,CAAC,SAAS,CAAC;;;AAG1F,QAAG,aAAa,EAAC;AAChB,YAAO,CAAC,GAAG,CAAC,EAAC,MAAM,EAAC,QAAQ,CAAC,MAAM,EAAC,CAAC,CAAC;AACtC,SAAI,CAAC,GAAG,CAAC,EAAC,YAAY,EAAC,GAAG,EAAC,CAAC,CAAC;KAC7B;;AAED,eAAW,CAAC,GAAG,CAAC,CAAC;IACjB,EAAC,UAAU,CAAC,CAAC;GACd,CAAC,CAAC,OAAO,CAAC,QAAQ,CAAC,CAAC;EAErB,CAAC,CAAC;;;AAGH,UAAS,UAAU,GAAE;AACpB,MAAI,CAAC,QAAQ,CAAC,IAAI,EAAE,KAAK,CAAC,CAAC;EAC3B;;;AAGD,UAAS,IAAI,CAAC,IAAI,EAAC,UAAU,EAAC;AAC7B,KAAG,CAAC,MAAM,CAAC,YAAY,EAAE,UAAU,CAAC,CAAC;AACrC,MAAI,GAAG,IAAI,CAAC,OAAO,CAAC,KAAK,EAAC,EAAE,CAAC,CAAC;AAC9B,KAAG,CAAC,IAAI,EAAE,CAAC,QAAQ,CAAC,IAAI,EAAC,QAAQ,EAAC;AACjC,SAAM,EAAC,MAAM;AACb,OAAI,EAAC,GAAG;GACR,CAAC,CAAC;AACH,MAAG,UAAU,KAAK,KAAK,EAAC;AACvB,OAAI,CAAC,GAAG,QAAQ,CAAC;AACjB,WAAQ,CAAC,IAAI,GAAI,CAAC,CAAC,QAAQ,GAAC,IAAI,GAAC,CAAC,CAAC,IAAI,GAAC,CAAC,CAAC,QAAQ,GAAC,KAAK,GAAC,IAAI,CAAC,MAAM,CAAC,CAAC,CAAC,AAAC,CAAC;GACzE;AACD,KAAG,CAAC,IAAI,CAAC,YAAY,EAAE,UAAU,CAAC,CAAC;EACnC;;;AAID,UAAS,WAAW,CAAC,GAAG,EAAC;AACxB,MAAI,MAAM,GAAG,GAAG;MAChB,OAAO;MAAE,IAAI;MAAE,MAAM;MAAE,KAAK;MAAE,MAAM,CAAC;AACrC,KAAG,CAAC,MAAM,CAAC,YAAY,EAAE,UAAU,CAAC,CAAC;AACrC,OAAI,IAAI,CAAC,GAAC,aAAa,EAAC,CAAC,GAAC,CAAC,EAAC,CAAC,EAAE,EAAC;AAC/B,OAAG,QAAQ,CAAC,CAAC,GAAC,CAAC,CAAC,CAAC,GAAG,IAAI,GAAG,GAAC,MAAM,EAAC;AAClC,cAAU,CAAC,WAAW,CAAC,SAAS,CAAC,CAAC;AAClC,WAAO,GAAG,UAAU,CAAC,EAAE,CAAC,CAAC,GAAC,CAAC,CAAC,CAAC;AAC7B,WAAO,CAAC,QAAQ,CAAC,SAAS,CAAC,CAAC;;AAE5B,UAAM,GAAG,OAAO,CAAC,MAAM,EAAE,CAAC,MAAM,EAAE,CAAC;AACnC,QAAI,GAAG,OAAO,CAAC,IAAI,EAAE,CAAC;;AAEtB,UAAM,GAAG,IAAI,CAAC,EAAE,CAAC,IAAI,CAAC,CAAC;AACvB,SAAK,GAAG,CAAC,MAAM,CAAC,EAAE,CAAC,iBAAiB,CAAC,CAAC;;AAEtC,OAAG,CAAC,IAAI,CAAC,YAAY,CAAC,CAAC,GAAG,CAAC,MAAM,CAAC,CAAC,OAAO,CAAC,MAAM,CAAC,CAAC;AACnD,QAAG,KAAK,EAAC;AACR,WAAM,CAAC,IAAI,EAAE,CAAC,QAAQ,CAAC,SAAS,CAAC,CAAC;AAClC,WAAM,CAAC,IAAI,EAAE,CAAC,SAAS,CAAC,MAAM,CAAC,CAAC;KAChC,MAAK,IAAG,MAAM,EAAC;AACf,SAAI,CAAC,IAAI,EAAE,CAAC,SAAS,CAAC,MAAM,CAAC,CAAC;KAC9B;AACD,OAAG,CAAC,IAAI,CAAC,YAAY,EAAE,UAAU,CAAC,CAAC;AACnC,UAAM;IACN,CAAC;GACF;EACD;CAGD,CAAC,CAAC","file":"/plugins/revolution-slider/documentation/js/script.js.map","sourcesContent":["/*!\r\n * Documenter 1.6\r\n * http://rxa.li/documenter\r\n *\r\n * Copyright 2011, Xaver Birsak\r\n * http://revaxarts.com\r\n *\r\n */\r\n//if Cufon replace headings\r\nif(typeof Cufon == 'function') Cufon.replace('h1, h2, h3, h4, h5, h6');\r\n \r\n$(document).ready(function() {\r\n\tvar timeout,\r\n\t\tsections = new Array(),\r\n\t\tsectionscount = 0,\r\n\t\twin = $(window),\r\n\t\tsidebar = $('#documenter_sidebar'),\r\n\t\tnav = $('#documenter_nav'),\r\n\t\tlogo = $('#documenter_logo'),\r\n\t\tnavanchors = nav.find('a'),\r\n\t\ttimeoffset = 50,\r\n\t\thash = location.hash || null;\r\n\t\tiDeviceNotOS4 = (navigator.userAgent.match(/iphone|ipod|ipad/i) && !navigator.userAgent.match(/OS 5/i)) || false,\r\n\t\tbadIE = $('html').prop('class').match(/ie(6|7|8)/)|| false;\r\n\t\t\r\n\t//handle external links (new window)\r\n\t$('a[href^=http]').bind('click',function(){\r\n\t\twindow.open($(this).attr('href'));\r\n\t\treturn false;\r\n\t});\r\n\t\r\n\t//IE 8 and lower doesn't like the smooth pagescroll\r\n\tif(!badIE){\r\n\t\twindow.scroll(0,0);\r\n\t\t\r\n\t\t$('a[href^=#]').bind('click touchstart',function(){\r\n\t\t\thash = $(this).attr('href');\r\n\t\t\t$.scrollTo.window().queue([]).stop();\r\n\t\t\tgoTo(hash);\r\n\t\t\treturn false;\r\n\t\t});\r\n\t\t\r\n\t\t//if a hash is set => go to it\r\n\t\tif(hash){\r\n\t\t\tsetTimeout(function(){\r\n\t\t\t\tgoTo(hash);\r\n\t\t\t},500);\r\n\t\t}\r\n\t}\r\n\t\r\n\t\r\n\t//We need the position of each section until the full page with all images is loaded\r\n\twin.bind('load',function(){\r\n\t\t\r\n\t\tvar sectionselector = 'section';\r\n\t\t\r\n\t\t//Documentation has subcategories\t\t\r\n\t\tif(nav.find('ol').length){\r\n\t\t\tsectionselector = 'section, h4';\r\n\t\t}\r\n\t\t//saving some information\r\n\t\t$(sectionselector).each(function(i,e){\r\n\t\t\tvar _this = $(this);\r\n\t\t\tvar p = {\r\n\t\t\t\tid: this.id,\r\n\t\t\t\tpos: _this.offset().top\r\n\t\t\t};\r\n\t\t\tsections.push(p);\r\n\t\t});\r\n\t\t\r\n\t\t\r\n\t\t//iPhone, iPod and iPad don't trigger the scroll event\r\n\t\tif(iDeviceNotOS4){\r\n\t\t\tnav.find('a').bind('click',function(){\r\n\t\t\t\tsetTimeout(function(){\r\n\t\t\t\t\twin.trigger('scroll');\t\t\t\t\r\n\t\t\t\t},duration);\r\n\t\t\t\t\r\n\t\t\t});\r\n\t\t\t//scroll to top\r\n\t\t\twindow.scroll(0,0);\r\n\t\t}\r\n\r\n\t\t//how many sections\r\n\t\tsectionscount = sections.length;\r\n\t\t\r\n\t\t//bind the handler to the scroll event\r\n\t\twin.bind('scroll',function(event){\r\n\t\t\tclearInterval(timeout);\r\n\t\t\t//should occur with a delay\r\n\t\t\ttimeout = setTimeout(function(){\r\n\t\t\t\t//get the position from the very top in all browsers\r\n\t\t\t\tpos = window.pageYOffset || document.documentElement.scrollTop || document.body.scrollTop;\r\n\t\t\t\t\r\n\t\t\t\t//iDeviceNotOS4s don't know the fixed property so we fake it\r\n\t\t\t\tif(iDeviceNotOS4){\r\n\t\t\t\t\tsidebar.css({height:document.height});\r\n\t\t\t\t\tlogo.css({'margin-top':pos});\r\n\t\t\t\t}\r\n\t\t\t\t//activate Nav element at the current position\r\n\t\t\t\tactivateNav(pos);\r\n\t\t\t},timeoffset);\r\n\t\t}).trigger('scroll');\r\n\r\n\t});\r\n\t\r\n\t//the function is called when the hash changes\r\n\tfunction hashchange(){\r\n\t\tgoTo(location.hash, false);\r\n\t}\r\n\t\r\n\t//scroll to a section and set the hash\r\n\tfunction goTo(hash,changehash){\r\n\t\twin.unbind('hashchange', hashchange);\r\n\t\thash = hash.replace(/!\\//,'');\r\n\t\twin.stop().scrollTo(hash,duration,{\r\n\t\t\teasing:easing,\r\n\t\t\taxis:'y'\t\t\t\r\n\t\t});\r\n\t\tif(changehash !== false){\r\n\t\t\tvar l = location;\r\n\t\t\tlocation.href = (l.protocol+'//'+l.host+l.pathname+'#!/'+hash.substr(1));\r\n\t\t}\r\n\t\twin.bind('hashchange', hashchange);\r\n\t}\r\n\t\r\n\t\r\n\t//activate current nav element\r\n\tfunction activateNav(pos){\r\n\t\tvar offset = 100,\r\n\t\tcurrent, next, parent, isSub, hasSub;\r\n\t\twin.unbind('hashchange', hashchange);\r\n\t\tfor(var i=sectionscount;i>0;i--){\r\n\t\t\tif(sections[i-1].pos <= pos+offset){\r\n\t\t\t\tnavanchors.removeClass('current');\r\n\t\t\t\tcurrent = navanchors.eq(i-1);\r\n\t\t\t\tcurrent.addClass('current');\r\n\t\t\t\t\r\n\t\t\t\tparent = current.parent().parent();\r\n\t\t\t\tnext = current.next();\r\n\t\t\t\t\r\n\t\t\t\thasSub = next.is('ol');\r\n\t\t\t\tisSub = !parent.is('#documenter_nav');\r\n\t\t\t\t\r\n\t\t\t\tnav.find('ol:visible').not(parent).slideUp('fast');\r\n\t\t\t\tif(isSub){\r\n\t\t\t\t\tparent.prev().addClass('current');\r\n\t\t\t\t\tparent.stop().slideDown('fast');\r\n\t\t\t\t}else if(hasSub){\r\n\t\t\t\t\tnext.stop().slideDown('fast');\r\n\t\t\t\t}\r\n\t\t\t\twin.bind('hashchange', hashchange);\r\n\t\t\t\tbreak;\r\n\t\t\t};\r\n\t\t}\t\r\n\t}\r\n\t\r\n\t\r\n});"]},"hash":"e60d1982ee10df5e6da997813291ee2adc5cf14d"}
